rembrandtml/__init__.py
rembrandtml/configuration.py
rembrandtml/core.py
rembrandtml/data.py
rembrandtml/entities.py
rembrandtml/factories.py
rembrandtml/functions.py
rembrandtml/models.py
rembrandtml/nnmodels.py
rembrandtml/runner.py
rembrandtml/utils.py
rembrandtml/visualization.py
rembrandtml-0.1.2a1.dist-info/DESCRIPTION.rst
rembrandtml-0.1.2a1.dist-info/METADATA
rembrandtml-0.1.2a1.dist-info/RECORD
rembrandtml-0.1.2a1.dist-info/WHEEL
rembrandtml-0.1.2a1.dist-info/metadata.json
rembrandtml-0.1.2a1.dist-info/top_level.txt
