Metadata-Version: 2.0
Name: rembrandtml
Version: 0.1.2a1
Summary: UNKNOWN
Home-page: UNKNOWN
Author: Tim Kiely
Author-email: UNKNOWN
License: Apache License 2.0
Keywords: development machinelearning deeplearning
Platform: UNKNOWN
Classifier: Development Status :: 3 - Alpha
Classifier: Intended Audience :: Developers
Classifier: Topic :: Scientific/Engineering :: Artificial Intelligence
Classifier: Topic :: Software Development :: Libraries :: Application Frameworks
Classifier: Programming Language :: Python :: 3.6
Classifier: License :: OSI Approved :: Apache Software License
Requires-Python: >=3
